{"cameraMode":{"drawMode":0,"name":"Shaded","section":"Shading Mode"},"sceneLighting":false,"audioPlay":false,"sceneViewState":{"m_AlwaysRefresh":false,"showFog":true,"showSkybox":false,"showFlares":true,"showImageEffects":true,"showParticleSystems":true,"showVisualEffectGraphs":true,"m_FxEnabled":true},"in2DMode":false,"pivot":{"x":-0.5486782789230347,"y":2.5208916664123537,"z":-0.4406093657016754},"rotation":{"x":-0.1699744015932083,"y":0.6714408993721008,"z":-0.16240601241588593,"w":-0.7027862071990967},"size":1.1079260110855103,"orthographic":false}